tinet/APIRequest.py
tinet/ApiConfig.py
tinet/LogUtil.py
tinet/RequestUtil.py
tinet/SignUtil.py
tinet/YamlUtil.py
tinet/__init__.py
TinetApiRequest-1.3.1.dist-info/METADATA
TinetApiRequest-1.3.1.dist-info/WHEEL
TinetApiRequest-1.3.1.dist-info/top_level.txt
TinetApiRequest-1.3.1.dist-info/RECORD
